svtk/__init__.py
svtk/tk_integration.py
svtk/util.py
svtk/lib/__init__.py
svtk/vtk_classes/__init__.py
svtk/vtk_classes/vtk_animation_timer_callback.py
svtk/vtk_classes/vtk_displayer.py
svtk/vtk_classes/vtk_keypress_interactor_style.py
svtk-0.2.0.dist-info/LICENSE.md
svtk-0.2.0.dist-info/METADATA
svtk-0.2.0.dist-info/WHEEL
svtk-0.2.0.dist-info/entry_points.txt
svtk-0.2.0.dist-info/top_level.txt
svtk-0.2.0.dist-info/RECORD
